hrmpython/__init__.py
hrmpython/main.py
hrmpython-0.1.dist-info/METADATA
hrmpython-0.1.dist-info/WHEEL
hrmpython-0.1.dist-info/RECORD
