Metadata-Version: 2.1
Name: hrmpython
Version: 0.1
Summary: A simple package to handle HRM data in python
Author-email: Satrio Wibowo <satrio.biology@yahoo.com>
Requires-Python: >=3.8
